pomdp_py/__init__.py
pomdp_py/__main__.py
pomdp_py/representations/__init__.py
pomdp_py/representations/belief/__init__.py
pomdp_py/representations/belief/particles.cpython-38-x86_64-linux-gnu.so
pomdp_py/representations/belief/histogram.py
pomdp_py/representations/distribution/__init__.py
pomdp_py/representations/distribution/gaussian.cpython-38-x86_64-linux-gnu.so
pomdp_py/representations/distribution/histogram.cpython-38-x86_64-linux-gnu.so
pomdp_py/representations/distribution/particles.cpython-38-x86_64-linux-gnu.so
pomdp_py/algorithms/value_function.py
pomdp_py/algorithms/__init__.py
pomdp_py/algorithms/po_uct.cpython-38-x86_64-linux-gnu.so
pomdp_py/algorithms/value_iteration.cpython-38-x86_64-linux-gnu.so
pomdp_py/algorithms/po_rollout.cpython-38-x86_64-linux-gnu.so
pomdp_py/algorithms/pomcp.cpython-38-x86_64-linux-gnu.so
pomdp_py/algorithms/bsp/__init__.py
pomdp_py/algorithms/bsp/blqr.py
pomdp_py/problems/__init__.py
pomdp_py/problems/lasertag/__init__.py
pomdp_py/problems/tag/constants.py
pomdp_py/problems/tag/__init__.py
pomdp_py/problems/tag/problem.py
pomdp_py/problems/tag/example_worlds.py
pomdp_py/problems/tag/experiment.py
pomdp_py/problems/tag/models/reward_model.py
pomdp_py/problems/tag/models/observation_model.py
pomdp_py/problems/tag/models/__init__.py
pomdp_py/problems/tag/models/transition_model.py
pomdp_py/problems/tag/models/policy_model.py
pomdp_py/problems/tag/models/components/__init__.py
pomdp_py/problems/tag/models/components/motion_policy.py
pomdp_py/problems/tag/models/components/grid_map.py
pomdp_py/problems/tag/env/__init__.py
pomdp_py/problems/tag/env/visual.py
pomdp_py/problems/tag/env/env.py
pomdp_py/problems/tag/domain/__init__.py
pomdp_py/problems/tag/domain/observation.py
pomdp_py/problems/tag/domain/state.py
pomdp_py/problems/tag/domain/action.py
pomdp_py/problems/tag/agent/__init__.py
pomdp_py/problems/tag/agent/agent.py
pomdp_py/problems/rocksample/__init__.py
pomdp_py-1.3.5.1.dist-info/RECORD
pomdp_py-1.3.5.1.dist-info/METADATA
pomdp_py-1.3.5.1.dist-info/WHEEL
pomdp_py-1.3.5.1.dist-info/top_level.txt
pomdp_py-1.3.5.1.dist-info/LICENSE
