Metadata-Version: 2.1
Name: pomdp-py
Version: 1.3.5.1
Summary: Python POMDP Library.
Author-email: Kaiyu Zheng <kzheng10@cs.brown.edu>
License: The MIT License (MIT)
Project-URL: Home, https://github.com/h2r/pomdp-py
Keywords: Partially Observable Markov Decision Process,POMDP
Classifier: Development Status :: 4 - Beta
Classifier: Intended Audience :: Developers
Classifier: Intended Audience :: Science/Research
Classifier: License :: OSI Approved :: MIT License
Classifier: Operating System :: OS Independent
Classifier: Programming Language :: Python
Classifier: Programming Language :: Cython
Classifier: Topic :: Scientific/Engineering
License-File: LICENSE
Requires-Dist: numpy >=1.18.0
Requires-Dist: scipy >=1.6.0
Requires-Dist: tqdm >=4.55.0
Provides-Extra: problems
Requires-Dist: matplotlib >=3.2.0 ; extra == 'problems'
Requires-Dist: pygame >=2.0.2 ; extra == 'problems'
Requires-Dist: opencv-python >=4.5.2.0 ; extra == 'problems'
